{"expireTime":9007200844108124000,"key":"transformer-remark-markdown-html-ast-cae567f3f4f325ac85f84cb0a0e306a8-gatsby-remark-imagesgatsby-remark-responsive-iframegatsby-remark-prismjsgatsby-remark-copy-linked-filesgatsby-remark-smartypants-","val":{"type":"root","children":[{"type":"element","tagName":"p","properties":{},"children":[{"type":"text","value":"Sorry F. Scott Fitzgerald, but The Great Gatsby now belongs to the JavaScript framework. I’m a big fan of this framework and I’ve used it to create both this blog and my personal ","position":{"start":{"line":2,"column":1,"offset":1},"end":{"line":2,"column":180,"offset":180}}},{"type":"element","tagName":"img","properties":{"src":"zamudio.netlify.app","alt":"portfolio site"},"children":[],"position":{"start":{"line":2,"column":180,"offset":180},"end":{"line":2,"column":218,"offset":218}}}],"position":{"start":{"line":2,"column":1,"offset":1},"end":{"line":2,"column":218,"offset":218}}}],"position":{"start":{"line":1,"column":1,"offset":0},"end":{"line":3,"column":1,"offset":219}}}}